Metadata-Version: 2.1
Name: syswow
Version: 0.1.0
Summary: DLL Injection
Author: syswow
Author-email: 64syswow64@protonmail.com
License: UNKNOWN
Keywords: DLLinjector,DLL
Platform: UNKNOWN
License-File: LICENCE
